firebird/__init__.py
firebird/base.py
firebird/client.py
firebird/compiler.py
firebird/creation.py
firebird/expressions.py
firebird/features.py
firebird/introspection.py
firebird/operations.py
firebird/schema.py
firebird/validation.py
firebird/version.py
django_firebird-2.2.1.dist-info/LICENSE
django_firebird-2.2.1.dist-info/METADATA
django_firebird-2.2.1.dist-info/WHEEL
django_firebird-2.2.1.dist-info/top_level.txt
django_firebird-2.2.1.dist-info/RECORD
